{
  "plugin_id": "owner-track",
  "name": "Owner Track Bundle",
  "plugin_version": "1.0.0",
  "bundle_type": "removable",
  "load_strategy": "manifest_driven",
  "removable": true,
  "track": "framework_owner",
  "enabled_by_default": true,
  "description": "Removable owner bundle that carries framework-development commands, docs, governance, and owner-only controls.",
  "command_surface": [
    "kvdf evolution",
    "kvdf evolution roadmap",
    "kvdf evolution partition",
    "kvdf evolution priorities"
  ],
  "docs_surface": [
    "plugins/owner-track/docs/index.md",
    "knowledge/governance/EVOLUTION_STEWARD.md",
    "docs/reports/KVDF_CORE_PLUGIN_CAPABILITY_SPLIT_STUDY.md"
  ]
}
